{
  "items" : {
    "item0" : {
      "isCompleted" : true,
      "task" : "mow the lawn",
      "uid": "g0VIcX726HXCV0H4A31d0GmeCOS2"
    },
    "item1" : {
      "isCompleted" : false,
      "task" : "grade quizzes",
      "uid": "g0VIcX726HXCV0H4A31d0GmeCOS2"
    },
    "item2" : {
      "isCompleted" : false,
      "task" : "take a nap",
      "uid": "bTevPJTRHXcIMugwE97F4plIm703"
    }
  },
  "users":{
    "user0":{
      "uid": "g0VIcX726HXCV0H4A31d0GmeCOS2",
      "username": "a"
    },
    "user1":{
      "uid": "bTevPJTRHXcIMugwE97F4plIm703",
      "username": "z"
    }
  }
}